<?xml version="1.0" encoding="utf-8"?>
<labels>
	<label index="general">Общие</label>
	<label index="general.use">Использовать/показывать поиск</label>
	<label index="general.area">Использовать область поиска</label>
	<label index="filtersets">Наборы фильтров</label>
	<label index="filtersets.save">Сохранить условия как набор фильтров</label>
	<label index="filtersets.deleteAll">Удалить все наборы фильтров</label>
	<label index="filtersets.hideAll">Спрятать все наборы фильтров</label>
	<label index="filtersets.renameAll">Переименовать все наборы фмльтров</label>
</labels>